[
  {
    "titre": "Lego Pirates soldats NEUF",
    "lienURL": "https://www.vinted.fr/items/5374900958-lego-pirates-soldats-neuf",
    "price": "6.0",
    "favourite": 12
  },
  {
    "titre": "Lego Pirates drapeau NEUF",
    "lienURL": "https://www.vinted.fr/items/5385495926-lego-pirates-drapeau-neuf",
    "price": "10.0",
    "favourite": 0
  },
  {
    "titre": "Lego Minifigures Lotto Gendarmi Pirati 10320",
    "lienURL": "https://www.vinted.fr/items/3944921794-lego-minifigures-lotto-gendarmi-pirati-10320",
    "price": "25.0",
    "favourite": 41
  },
  {
    "titre": "Lego Figuren Forestmen & Dorfbewohner - NEU - 31109 21322 10320",
    "lienURL": "https://www.vinted.fr/items/3582254676-lego-figuren-forestmen-dorfbewohner-neu-31109-21322-10320",
    "price": "5.0",
    "favourite": 2
  },
  {
    "titre": "Lego Pirates gouverneur NEUF",
    "lienURL": "https://www.vinted.fr/items/5385502500-lego-pirates-gouverneur-neuf",
    "price": "10.0",
    "favourite": 0
  },
  {
    "titre": "LEGO 1 minifigure from Eldorado Fortress (10320)",
    "lienURL": "https://www.vinted.fr/items/4512676005-lego-1-minifigure-from-eldorado-fortress-10320",
    "price": "11.0",
    "favourite": 7
  },
  {
    "titre": "Lego Flag 2 x 2 Jolly Roger 6446963 Eldorado Fortress set 10320",
    "lienURL": "https://www.vinted.fr/items/4543884111-lego-flag-2-x-2-jolly-roger-6446963-eldorado-fortress-set-10320",
    "price": "3.0",
    "favourite": 1
  },
  {
    "titre": "Lego 10320 | Eldorado Fortress",
    "lienURL": "https://www.vinted.fr/items/5275550300-lego-10320-eldorado-fortress",
    "price": "29.0",
    "favourite": 8
  },
  {
    "titre": "Lego 10320 | 2x mini upper parts (new)",
    "lienURL": "https://www.vinted.fr/items/4215660364-lego-10320-2x-mini-upper-parts-new",
    "price": "5.0",
    "favourite": 1
  },
  {
    "titre": "Lego minifigures Pirates 10320 nuove",
    "lienURL": "https://www.vinted.fr/items/5100647842-lego-minifigures-pirates-10320-nuove",
    "price": "50.0",
    "favourite": 5
  },
  {
    "titre": "6 Minifigures LEGO pirati - pirates + accessori",
    "lienURL": "https://www.vinted.fr/items/4839130784-6-minifigures-lego-pirati-pirates-accessori",
    "price": "35.0",
    "favourite": 13
  },
  {
    "titre": "Lego Pirate Imperial Soldier",
    "lienURL": "https://www.vinted.fr/items/4660910964-lego-pirate-imperial-soldier",
    "price": "8.0",
    "favourite": 2
  },
  {
    "titre": "Minifiguras Lego set 10320",
    "lienURL": "https://www.vinted.fr/items/4255442551-minifiguras-lego-set-10320",
    "price": "35.0",
    "favourite": 10
  },
  {
    "titre": "Lego Pirate Imperial Soldier",
    "lienURL": "https://www.vinted.fr/items/4660910237-lego-pirate-imperial-soldier",
    "price": "8.0",
    "favourite": 1
  },
  {
    "titre": "Lego White Brick, Modified Facet 3 x 3",
    "lienURL": "https://www.vinted.fr/items/4314957842-lego-white-brick-modified-facet-3-x-3",
    "price": "1.5",
    "favourite": 9
  },
  {
    "titre": "LEGO 6 minifigures soldati imperiali - Ammiraglio + gabbiano",
    "lienURL": "https://www.vinted.fr/items/4712699879-lego-6-minifigures-soldati-imperiali-ammiraglio-gabbiano",
    "price": "48.0",
    "favourite": 10
  },
  {
    "titre": "Lego minifigure medievale castle per 10305 10320",
    "lienURL": "https://www.vinted.fr/items/3306863152-lego-minifigure-medievale-castle-per-10305-10320",
    "price": "19.9",
    "favourite": 16
  },
  {
    "titre": "Lego 10320 - Eldorado Festung",
    "lienURL": "https://www.vinted.fr/items/5429194923-lego-10320-eldorado-festung",
    "price": "175.0",
    "favourite": 1
  },
  {
    "titre": "2 Minifigures Lego Imperial Soldier",
    "lienURL": "https://www.vinted.fr/items/4219657485-2-minifigures-lego-imperial-soldier",
    "price": "12.0",
    "favourite": 3
  },
  {
    "titre": "Lego Icons - 10320 (nuovo misb)",
    "lienURL": "https://www.vinted.fr/items/5415759891-lego-icons-10320-nuovo-misb",
    "price": "186.0",
    "favourite": 21
  },
  {
    "titre": "Lego 10320 la forteresse de l’eldorado",
    "lienURL": "https://www.vinted.fr/items/4881780283-lego-10320-la-forteresse-de-leldorado",
    "price": "190.0",
    "favourite": 39
  },
  {
    "titre": "Lote lego minifiguras 10320",
    "lienURL": "https://www.vinted.fr/items/4958953585-lote-lego-minifiguras-10320",
    "price": "65.0",
    "favourite": 1
  },
  {
    "titre": "Lego 10320 nuovo",
    "lienURL": "https://www.vinted.fr/items/5184157061-lego-10320-nuovo",
    "price": "190.0",
    "favourite": 13
  },
  {
    "titre": "Lego 10320 fortezza di eldorado",
    "lienURL": "https://www.vinted.fr/items/4367379352-lego-10320-fortezza-di-eldorado",
    "price": "195.0",
    "favourite": 19
  },
  {
    "titre": "Lego pirates",
    "lienURL": "https://www.vinted.fr/items/5348041712-lego-pirates",
    "price": "230.0",
    "favourite": 5
  },
  {
    "titre": "Lego 10320 Eldorado Fortress",
    "lienURL": "https://www.vinted.fr/items/5263166787-lego-10320-eldorado-fortress",
    "price": "200.0",
    "favourite": 4
  },
  {
    "titre": "LEGO Icons La forteresse de l’Eldorado",
    "lienURL": "https://www.vinted.fr/items/5052275190-lego-icons-la-forteresse-de-leldorado",
    "price": "199.0",
    "favourite": 11
  },
  {
    "titre": "Lego 10320",
    "lienURL": "https://www.vinted.fr/items/5010045497-lego-10320",
    "price": "200.0",
    "favourite": 12
  },
  {
    "titre": "Lego 10320 Fortezza di Eldorado MISB",
    "lienURL": "https://www.vinted.fr/items/3824747552-lego-10320-fortezza-di-eldorado-misb",
    "price": "199.0",
    "favourite": 18
  },
  {
    "titre": "Lego Icons 10320",
    "lienURL": "https://www.vinted.fr/items/5150205096-lego-icons-10320",
    "price": "210.0",
    "favourite": 6
  },
  {
    "titre": "Lego 10320 Eldorado Fortress",
    "lienURL": "https://www.vinted.fr/items/3837313756-lego-10320-eldorado-fortress",
    "price": "205.0",
    "favourite": 22
  },
  {
    "titre": "Lego 10320 Fortress Eldorado Misb New",
    "lienURL": "https://www.vinted.fr/items/5179809631-lego-10320-fortress-eldorado-misb-new",
    "price": "210.0",
    "favourite": 6
  }
]