[
  {
    "titre": "Plaque lego 11024",
    "lienURL": "https://www.vinted.fr/items/5544152733-plaque-lego-11024",
    "price": "12.0",
    "favourite": 7,
    "image": "19/12/2024"
  },
  {
    "titre": "LEGO Classic 11024 Graue Bauplatte Bausatz, Grau",
    "lienURL": "https://www.vinted.fr/items/4299134432-lego-classic-11024-graue-bauplatte-bausatz-grau",
    "price": "7.0",
    "favourite": 15,
    "image": "01/04/2024"
  },
  {
    "titre": "Plaque lego grise 11024",
    "lienURL": "https://www.vinted.fr/items/2916321960-plaque-lego-grise-11024",
    "price": "17.0",
    "favourite": 13,
    "image": "17/04/2023"
  },
  {
    "titre": "Lego Grijze bouwplaat 38 x 38 cm (11024)",
    "lienURL": "https://www.vinted.fr/items/5311049686-lego-grijze-bouwplaat-38-x-38-cm-11024",
    "price": "10.0",
    "favourite": 2,
    "image": "01/11/2024"
  },
  {
    "titre": "Lego bouwplaat 11024",
    "lienURL": "https://www.vinted.fr/items/4978917502-lego-bouwplaat-11024",
    "price": "25.0",
    "favourite": 18,
    "image": "02/09/2024"
  },
  {
    "titre": "Lego 11024 Classic La plaque de construction grise",
    "lienURL": "https://www.vinted.fr/items/4897199763-lego-11024-classic-la-plaque-de-construction-grise",
    "price": "12.0",
    "favourite": 14,
    "image": "17/08/2024"
  },
  {
    "titre": "LEGO Plaque de construction Grise 11024",
    "lienURL": "https://www.vinted.fr/items/5365407093-lego-plaque-de-construction-grise-11024",
    "price": "12.0",
    "favourite": 2,
    "image": "11/11/2024"
  },
  {
    "titre": "2 Lego Bauplatten",
    "lienURL": "https://www.vinted.fr/items/5244197755-2-lego-bauplatten",
    "price": "12.0",
    "favourite": 11,
    "image": "19/10/2024"
  },
  {
    "titre": "Lego Placa de Construção Cinza",
    "lienURL": "https://www.vinted.fr/items/3345033902-lego-placa-de-construcao-cinza",
    "price": "11.99",
    "favourite": 45,
    "image": "13/08/2023"
  },
  {
    "titre": "2 plaques Lego 11024",
    "lienURL": "https://www.vinted.fr/items/5156192528-2-plaques-lego-11024",
    "price": "24.0",
    "favourite": 5,
    "image": "27/12/2024"
  },
  {
    "titre": "2 lego bouwplaten grondplaten baseplates set 6195 Neptune Discovery Lab",
    "lienURL": "https://www.vinted.fr/items/5552624215-2-lego-bouwplaten-grondplaten-baseplates-set-6195-neptune-discovery-lab",
    "price": "27.5",
    "favourite": 8,
    "image": "22/12/2024"
  },
  {
    "titre": "Lego bouwplaat grondplaat baseplate legoset 6761 2359px2 #Dex",
    "lienURL": "https://www.vinted.fr/items/5538381109-lego-bouwplaat-grondplaat-baseplate-legoset-6761-2359px2-dex",
    "price": "10.0",
    "favourite": 21,
    "image": "17/12/2024"
  },
  {
    "titre": "Lego set de 9 plaques de construction (11023 - 11024 - 11025 - vintage)",
    "lienURL": "https://www.vinted.fr/items/5419551259-lego-set-de-9-plaques-de-construction-11023-11024-11025-vintage",
    "price": "30.0",
    "favourite": 8,
    "image": "21/11/2024"
  },
  {
    "titre": "Planche lego classic 11024",
    "lienURL": "https://www.vinted.fr/items/3045606611-planche-lego-classic-11024",
    "price": "15.0",
    "favourite": 9,
    "image": "30/10/2023"
  },
  {
    "titre": "Lego bouwplaat grondplaat plaque set 6419 4478px3 #MV",
    "lienURL": "https://www.vinted.fr/items/5523905472-lego-bouwplaat-grondplaat-plaque-set-6419-4478px3-mv",
    "price": "6.0",
    "favourite": 6,
    "image": "14/12/2024"
  },
  {
    "titre": "Lego bouwplaat grondplaat baseplate set 6380 6398 1682 #MV",
    "lienURL": "https://www.vinted.fr/items/5530618320-lego-bouwplaat-grondplaat-baseplate-set-6380-6398-1682-mv",
    "price": "5.0",
    "favourite": 7,
    "image": "15/12/2024"
  },
  {
    "titre": "Lego bouwplaat grondplaat baseplate 2359px2 set 6761",
    "lienURL": "https://www.vinted.fr/items/5490742247-lego-bouwplaat-grondplaat-baseplate-2359px2-set-6761",
    "price": "12.0",
    "favourite": 17,
    "image": "06/12/2024"
  },
  {
    "titre": "Legocity lego city 7280 wegplaten wegenplaten New",
    "lienURL": "https://www.vinted.fr/items/5385207406-legocity-lego-city-7280-wegplaten-wegenplaten-new",
    "price": "26.5",
    "favourite": 8,
    "image": "10/12/2024"
  },
  {
    "titre": "Lego bouwplaat grondplaat baseplate legoset 6382 fire station #C",
    "lienURL": "https://www.vinted.fr/items/5512820189-lego-bouwplaat-grondplaat-baseplate-legoset-6382-fire-station-c",
    "price": "2.5",
    "favourite": 8,
    "image": "11/12/2024"
  },
  {
    "titre": "Lego bouwplaat grondplaat baseplate 16x32 set 6410 Cabana Beach",
    "lienURL": "https://www.vinted.fr/items/5291290497-lego-bouwplaat-grondplaat-baseplate-16x32-set-6410-cabana-beach",
    "price": "9.0",
    "favourite": 20,
    "image": "28/10/2024"
  },
  {
    "titre": "Lego bouwplaat grondplaat baseplate set 6260 Shipwreck Island #MV",
    "lienURL": "https://www.vinted.fr/items/5523901717-lego-bouwplaat-grondplaat-baseplate-set-6260-shipwreck-island-mv",
    "price": "4.0",
    "favourite": 10,
    "image": "14/12/2024"
  },
  {
    "titre": "7 lego bouwplaten grondplaten baseplates 16x16",
    "lienURL": "https://www.vinted.fr/items/5127265032-7-lego-bouwplaten-grondplaten-baseplates-16x16",
    "price": "12.0",
    "favourite": 25,
    "image": "29/09/2024"
  },
  {
    "titre": "Lego bouwplaat grondplaat baseplate legoset 6386 4478px1 #DB",
    "lienURL": "https://www.vinted.fr/items/5499373773-lego-bouwplaat-grondplaat-baseplate-legoset-6386-4478px1-db",
    "price": "4.5",
    "favourite": 4,
    "image": "08/12/2024"
  },
  {
    "titre": "Lego classic + bouwplaat",
    "lienURL": "https://www.vinted.fr/items/5489422840-lego-classic-bouwplaat",
    "price": "40.0",
    "favourite": 1,
    "image": "06/12/2024"
  },
  {
    "titre": "5 groene lego bouwplaten grondplaten baseplates 16x16 16x32 24x32",
    "lienURL": "https://www.vinted.fr/items/5538261051-5-groene-lego-bouwplaten-grondplaten-baseplates-16x16-16x32-24x32",
    "price": "4.0",
    "favourite": 6,
    "image": "17/12/2024"
  },
  {
    "titre": "Lego bouwplaat grondplaat baseplate rood 24x32",
    "lienURL": "https://www.vinted.fr/items/5519437536-lego-bouwplaat-grondplaat-baseplate-rood-24x32",
    "price": "2.5",
    "favourite": 1,
    "image": "12/12/2024"
  },
  {
    "titre": "Lot de 6 plaques Lego 11024 et 1 plaque 11023",
    "lienURL": "https://www.vinted.fr/items/5436986881-lot-de-6-plaques-lego-11024-et-1-plaque-11023",
    "price": "55.0",
    "favourite": 6,
    "image": "24/11/2024"
  },
  {
    "titre": "Lego bouwplaat grondplaat plaque set 6368 4478px1 #MV",
    "lienURL": "https://www.vinted.fr/items/5523920780-lego-bouwplaat-grondplaat-plaque-set-6368-4478px1-mv",
    "price": "4.0",
    "favourite": 3,
    "image": "14/12/2024"
  },
  {
    "titre": "Lego 11024",
    "lienURL": "https://www.vinted.fr/items/3842945605-lego-11024",
    "price": "15.0",
    "favourite": 1,
    "image": "03/12/2023"
  },
  {
    "titre": "Lego baseplate grondplaat bouwplaat 16x32",
    "lienURL": "https://www.vinted.fr/items/5423050971-lego-baseplate-grondplaat-bouwplaat-16x32",
    "price": "4.0",
    "favourite": 2,
    "image": "22/11/2024"
  },
  {
    "titre": "7 lego bouwplaten grondplaten baseplates 16x32",
    "lienURL": "https://www.vinted.fr/items/5292798616-7-lego-bouwplaten-grondplaten-baseplates-16x32",
    "price": "22.5",
    "favourite": 3,
    "image": "28/10/2024"
  },
  {
    "titre": "Lego bouwplaten grondplaten baseplates 8x16",
    "lienURL": "https://www.vinted.fr/items/5290997786-lego-bouwplaten-grondplaten-baseplates-8x16",
    "price": "22.5",
    "favourite": 2,
    "image": "28/10/2024"
  },
  {
    "titre": "Lego 11024 Plate 48x48 - light bluish gray - pack of 10",
    "lienURL": "https://www.vinted.fr/items/5279194353-lego-11024-plate-48x48-light-bluish-gray-pack-of-10",
    "price": "120.0",
    "favourite": 0,
    "image": "26/10/2024"
  }
]