[
  {
    "titre": "Lego 71428",
    "lienURL": "https://www.vinted.fr/items/4951321529-lego-71428",
    "price": "5.0",
    "favourite": 0
  },
  {
    "titre": "lego 71428",
    "lienURL": "https://www.vinted.fr/items/5251883563-lego-71428",
    "price": "7.0",
    "favourite": 1
  },
  {
    "titre": "Lego 71428",
    "lienURL": "https://www.vinted.fr/items/5258549292-lego-71428",
    "price": "10.0",
    "favourite": 2
  },
  {
    "titre": "Lego super Mario",
    "lienURL": "https://www.vinted.fr/items/4654412248-lego-super-mario",
    "price": "10.0",
    "favourite": 5
  },
  {
    "titre": "Super Mario Nintendo Lego 71428 Yoshi Yoshis egg forest",
    "lienURL": "https://www.vinted.fr/items/5164036664-super-mario-nintendo-lego-71428-yoshi-yoshis-egg-forest",
    "price": "10.0",
    "favourite": 6
  },
  {
    "titre": "71428 Lego Super Mario Yoshi's wilder Wald",
    "lienURL": "https://www.vinted.fr/items/5195532159-71428-lego-super-mario-yoshis-wilder-wald",
    "price": "5.0",
    "favourite": 14
  },
  {
    "titre": "Lego Mario",
    "lienURL": "https://www.vinted.fr/items/5250862745-lego-mario",
    "price": "9.0",
    "favourite": 8
  },
  {
    "titre": "LEGO Super Mario 71428 Pack di Espansione Yoshi nella Foresta Fuovolosa - Usato",
    "lienURL": "https://www.vinted.fr/items/5364915146-lego-super-mario-71428-pack-di-espansione-yoshi-nella-foresta-fuovolosa-usato",
    "price": "15.0",
    "favourite": 4
  },
  {
    "titre": "NEUF - Lego Super Mario 71428",
    "lienURL": "https://www.vinted.fr/items/5390087380-neuf-lego-super-mario-71428",
    "price": "13.0",
    "favourite": 0
  },
  {
    "titre": "71428 Lego Super Mario Yoshi Expansion Set",
    "lienURL": "https://www.vinted.fr/items/4221058434-71428-lego-super-mario-yoshi-expansion-set",
    "price": "10.99",
    "favourite": 25
  }
]