[
  {
    "titre": "Lego super Mario plat 2x2 avec scanner code goomba",
    "lienURL": "https://www.vinted.fr/items/5138826658-lego-super-mario-plat-2x2-avec-scanner-code-goomba",
    "price": "1.2",
    "favourite": 2
  },
  {
    "titre": "Lego mariop 71437 -=NEUF=-",
    "lienURL": "https://www.vinted.fr/items/5544003601-lego-mariop-71437-neuf",
    "price": "80.0",
    "favourite": 2
  },
  {
    "titre": "Set Lego 71437 Treno Super Mario Bros",
    "lienURL": "https://www.vinted.fr/items/5346844546-set-lego-71437-treno-super-mario-bros",
    "price": "100.0",
    "favourite": 33
  },
  {
    "titre": "lego super mario 71437 le train de bowser",
    "lienURL": "https://www.vinted.fr/items/5493684607-lego-super-mario-71437-le-train-de-bowser",
    "price": "100.0",
    "favourite": 4
  }
]