[
  {
    "titre": "Lego 75344",
    "lienURL": "https://www.vinted.fr/items/5526995536-lego-75344",
    "price": "5.0",
    "favourite": 8
  },
  {
    "titre": "Lego Star Wars neuf numéro 75344",
    "lienURL": "https://www.vinted.fr/items/5497262271-lego-star-wars-neuf-numero-75344",
    "price": "7.0",
    "favourite": 4
  },
  {
    "titre": "LEGO star wars 75344",
    "lienURL": "https://www.vinted.fr/items/5519988638-lego-star-wars-75344",
    "price": "4.8",
    "favourite": 5
  },
  {
    "titre": "Lego 75344",
    "lienURL": "https://www.vinted.fr/items/5483374705-lego-75344",
    "price": "5.0",
    "favourite": 4
  },
  {
    "titre": "Lego star wars",
    "lienURL": "https://www.vinted.fr/items/5499114554-lego-star-wars",
    "price": "4.0",
    "favourite": 2
  },
  {
    "titre": "Lot lego Star Wars",
    "lienURL": "https://www.vinted.fr/items/5543657884-lot-lego-star-wars",
    "price": "20.0",
    "favourite": 9
  },
  {
    "titre": "Lego neuf star wars 75344",
    "lienURL": "https://www.vinted.fr/items/4984354393-lego-neuf-star-wars-75344",
    "price": "8.0",
    "favourite": 6
  },
  {
    "titre": "Lego star wars 75344 (nieuw)",
    "lienURL": "https://www.vinted.fr/items/5538506250-lego-star-wars-75344-nieuw",
    "price": "5.0",
    "favourite": 11
  },
  {
    "titre": "Lego Star Wars 75344",
    "lienURL": "https://www.vinted.fr/items/5489956159-lego-star-wars-75344",
    "price": "5.0",
    "favourite": 3
  },
  {
    "titre": "Lego Star Wars 75344",
    "lienURL": "https://www.vinted.fr/items/5388085936-lego-star-wars-75344",
    "price": "7.0",
    "favourite": 5
  },
  {
    "titre": "LEGO - Star Wars - 75344 - le Vaisseau de Boba Fett - Microfighter",
    "lienURL": "https://www.vinted.fr/items/5429618927-lego-star-wars-75344-le-vaisseau-de-boba-fett-microfighter",
    "price": "7.5",
    "favourite": 4
  },
  {
    "titre": "Lego ® figurine Star Wars – Boba Fett",
    "lienURL": "https://www.vinted.fr/items/5504144185-lego-r-figurine-star-wars-boba-fett",
    "price": "2.9",
    "favourite": 2
  },
  {
    "titre": "Lego star wars 75344",
    "lienURL": "https://www.vinted.fr/items/5414789131-lego-star-wars-75344",
    "price": "4.0",
    "favourite": 8
  },
  {
    "titre": "Lego 75344",
    "lienURL": "https://www.vinted.fr/items/4245556729-lego-75344",
    "price": "3.0",
    "favourite": 1
  },
  {
    "titre": "Lego star wars  boba fett's 75344",
    "lienURL": "https://www.vinted.fr/items/5530343069-lego-star-wars-boba-fetts-75344",
    "price": "8.0",
    "favourite": 3
  },
  {
    "titre": "Lego starwars 75344 boba fett’s starship microfighter",
    "lienURL": "https://www.vinted.fr/items/4409696430-lego-starwars-75344-boba-fetts-starship-microfighter",
    "price": "6.0",
    "favourite": 13
  },
  {
    "titre": "Lego Star Wars 75344 Boba Fett’s Starship Microfighter new in sealed box",
    "lienURL": "https://www.vinted.fr/items/5435315221-lego-star-wars-75344-boba-fetts-starship-microfighter-new-in-sealed-box",
    "price": "5.0",
    "favourite": 6
  },
  {
    "titre": "Lego 75344",
    "lienURL": "https://www.vinted.fr/items/5322004042-lego-75344",
    "price": "5.0",
    "favourite": 0
  },
  {
    "titre": "LEGO® Star Wars 75344 Le vaisseau de Boba Fett Microfighter",
    "lienURL": "https://www.vinted.fr/items/5536580185-legor-star-wars-75344-le-vaisseau-de-boba-fett-microfighter",
    "price": "8.0",
    "favourite": 5
  },
  {
    "titre": "Lego 75344",
    "lienURL": "https://www.vinted.fr/items/5511834661-lego-75344",
    "price": "7.0",
    "favourite": 3
  },
  {
    "titre": "Lego Star Wars 75344 Le vaisseau de Boba Fett Microfighter",
    "lienURL": "https://www.vinted.fr/items/5395159179-lego-star-wars-75344-le-vaisseau-de-boba-fett-microfighter",
    "price": "4.0",
    "favourite": 3
  },
  {
    "titre": "Lego 75344 stars wars microfighter neuf scellé",
    "lienURL": "https://www.vinted.fr/items/5501299596-lego-75344-stars-wars-microfighter-neuf-scelle",
    "price": "8.0",
    "favourite": 0
  },
  {
    "titre": "Lego 75344",
    "lienURL": "https://www.vinted.fr/items/4605253626-lego-75344",
    "price": "7.0",
    "favourite": 2
  },
  {
    "titre": "Lego 75344",
    "lienURL": "https://www.vinted.fr/items/5255218234-lego-75344",
    "price": "8.0",
    "favourite": 2
  },
  {
    "titre": "Lego 75344 - Star Wars ",
    "lienURL": "https://www.vinted.fr/items/4255400862-lego-75344-star-wars",
    "price": "5.0",
    "favourite": 8
  },
  {
    "titre": "Neuf Lego star wars 75344 pas de minifigs",
    "lienURL": "https://www.vinted.fr/items/5529135874-neuf-lego-star-wars-75344-pas-de-minifigs",
    "price": "9.9",
    "favourite": 0
  },
  {
    "titre": "Vaisseau de Bobba Fett microfighter",
    "lienURL": "https://www.vinted.fr/items/5487843725-vaisseau-de-bobba-fett-microfighter",
    "price": "10.0",
    "favourite": 1
  },
  {
    "titre": "Lego star wars 75344",
    "lienURL": "https://www.vinted.fr/items/5147104046-lego-star-wars-75344",
    "price": "7.0",
    "favourite": 0
  },
  {
    "titre": "Lego Star Wars",
    "lienURL": "https://www.vinted.fr/items/5498900110-lego-star-wars",
    "price": "10.0",
    "favourite": 3
  },
  {
    "titre": "Lego 75344 Boba Fett Microfighter",
    "lienURL": "https://www.vinted.fr/items/5536180446-lego-75344-boba-fett-microfighter",
    "price": "5.0",
    "favourite": 3
  },
  {
    "titre": "Lego Star War 75344",
    "lienURL": "https://www.vinted.fr/items/5502292629-lego-star-war-75344",
    "price": "10.0",
    "favourite": 2
  },
  {
    "titre": "Lego Star Wars 75344 Boba Fett's Starship Microfighter",
    "lienURL": "https://www.vinted.fr/items/5483144091-lego-star-wars-75344-boba-fetts-starship-microfighter",
    "price": "3.0",
    "favourite": 0
  },
  {
    "titre": "Lego Star wars NUOVO mai aperto Cod 75344",
    "lienURL": "https://www.vinted.fr/items/5538610496-lego-star-wars-nuovo-mai-aperto-cod-75344",
    "price": "7.0",
    "favourite": 2
  },
  {
    "titre": "Lego Star wars 75344",
    "lienURL": "https://www.vinted.fr/items/5439341860-lego-star-wars-75344",
    "price": "9.0",
    "favourite": 1
  },
  {
    "titre": "Lego Star Wars Boba Fett 75344 neuf",
    "lienURL": "https://www.vinted.fr/items/5514015720-lego-star-wars-boba-fett-75344-neuf",
    "price": "10.0",
    "favourite": 1
  },
  {
    "titre": "Lego Star Wars 75344",
    "lienURL": "https://www.vinted.fr/items/5468749137-lego-star-wars-75344",
    "price": "5.0",
    "favourite": 0
  },
  {
    "titre": "Lego 75344 - Boba Fett's Starship Microfighter",
    "lienURL": "https://www.vinted.fr/items/5083426957-lego-75344-boba-fetts-starship-microfighter",
    "price": "4.5",
    "favourite": 7
  },
  {
    "titre": "Boîte Lego Star Wars 75344",
    "lienURL": "https://www.vinted.fr/items/5506797115-boite-lego-star-wars-75344",
    "price": "15.0",
    "favourite": 1
  },
  {
    "titre": "Lego star wars 75344",
    "lienURL": "https://www.vinted.fr/items/5530991635-lego-star-wars-75344",
    "price": "7.0",
    "favourite": 4
  },
  {
    "titre": "Lots de mini vaisseaux star wars",
    "lienURL": "https://www.vinted.fr/items/5533218024-lots-de-mini-vaisseaux-star-wars",
    "price": "15.0",
    "favourite": 6
  },
  {
    "titre": "Lego 75344 Boba Fett microfighter.",
    "lienURL": "https://www.vinted.fr/items/3743790418-lego-75344-boba-fett-microfighter",
    "price": "7.0",
    "favourite": 3
  },
  {
    "titre": "Av lego starwars neuf",
    "lienURL": "https://www.vinted.fr/items/5173577149-av-lego-starwars-neuf",
    "price": "8.0",
    "favourite": 1
  },
  {
    "titre": "Lego star Wars boîte neuve ",
    "lienURL": "https://www.vinted.fr/items/3863280646-lego-star-wars-boite-neuve",
    "price": "9.99",
    "favourite": 1
  },
  {
    "titre": "Lego star wars 75344 scellé",
    "lienURL": "https://www.vinted.fr/items/5512521004-lego-star-wars-75344-scelle",
    "price": "9.0",
    "favourite": 3
  },
  {
    "titre": "Lego Star Wars 75344",
    "lienURL": "https://www.vinted.fr/items/5222117134-lego-star-wars-75344",
    "price": "7.0",
    "favourite": 4
  },
  {
    "titre": "Lego stars wars 75344",
    "lienURL": "https://www.vinted.fr/items/5373624778-lego-stars-wars-75344",
    "price": "6.99",
    "favourite": 2
  },
  {
    "titre": "Lego 75344",
    "lienURL": "https://www.vinted.fr/items/4642479744-lego-75344",
    "price": "8.0",
    "favourite": 2
  },
  {
    "titre": "Lego Stars Wars 75344 Boba Fett Starship",
    "lienURL": "https://www.vinted.fr/items/5113419917-lego-stars-wars-75344-boba-fett-starship",
    "price": "6.0",
    "favourite": 0
  },
  {
    "titre": "Lego 75344 star wars neuf",
    "lienURL": "https://www.vinted.fr/items/4304720659-lego-75344-star-wars-neuf",
    "price": "8.0",
    "favourite": 7
  },
  {
    "titre": "Lego star wars 75344 boba fett’s",
    "lienURL": "https://www.vinted.fr/items/5366199499-lego-star-wars-75344-boba-fetts",
    "price": "10.0",
    "favourite": 1
  },
  {
    "titre": "Lego star Wars 75344",
    "lienURL": "https://www.vinted.fr/items/5314990832-lego-star-wars-75344",
    "price": "8.0",
    "favourite": 2
  },
  {
    "titre": "Coppia Lego Star Wars Microfighter - 75295 e 75344",
    "lienURL": "https://www.vinted.fr/items/5493348325-coppia-lego-star-wars-microfighter-75295-e-75344",
    "price": "19.99",
    "favourite": 2
  },
  {
    "titre": "Lego Star Wars Microfighter Boba Fett - 75344",
    "lienURL": "https://www.vinted.fr/items/5493352156-lego-star-wars-microfighter-boba-fett-75344",
    "price": "9.99",
    "favourite": 6
  },
  {
    "titre": "Lego 75344",
    "lienURL": "https://www.vinted.fr/items/5331708321-lego-75344",
    "price": "5.0",
    "favourite": 1
  },
  {
    "titre": "LEGO 75344 Boba Fett's Microfighter NEW x5",
    "lienURL": "https://www.vinted.fr/items/5497029285-lego-75344-boba-fetts-microfighter-new-x5",
    "price": "25.0",
    "favourite": 5
  },
  {
    "titre": "Lego star wars 75344",
    "lienURL": "https://www.vinted.fr/items/5252085657-lego-star-wars-75344",
    "price": "8.0",
    "favourite": 2
  },
  {
    "titre": "Lego star wars",
    "lienURL": "https://www.vinted.fr/items/3746759647-lego-star-wars",
    "price": "7.0",
    "favourite": 4
  },
  {
    "titre": "Lego star wars",
    "lienURL": "https://www.vinted.fr/items/5509833728-lego-star-wars",
    "price": "4.0",
    "favourite": 8
  },
  {
    "titre": "Lego 75344 Star Wars Slave 1 Boba Fett Microfighter",
    "lienURL": "https://www.vinted.fr/items/5401990885-lego-75344-star-wars-slave-1-boba-fett-microfighter",
    "price": "9.0",
    "favourite": 4
  },
  {
    "titre": "Lego 75344",
    "lienURL": "https://www.vinted.fr/items/3461192104-lego-75344",
    "price": "5.0",
    "favourite": 0
  },
  {
    "titre": "Lego Boba Fett,s Starship 75344",
    "lienURL": "https://www.vinted.fr/items/5406453543-lego-boba-fetts-starship-75344",
    "price": "6.0",
    "favourite": 1
  },
  {
    "titre": "Lego star wars",
    "lienURL": "https://www.vinted.fr/items/5190586192-lego-star-wars",
    "price": "5.0",
    "favourite": 6
  },
  {
    "titre": "Lego 75344",
    "lienURL": "https://www.vinted.fr/items/4999615053-lego-75344",
    "price": "10.0",
    "favourite": 1
  },
  {
    "titre": "Lego set schiacciato Star world",
    "lienURL": "https://www.vinted.fr/items/5515513038-lego-set-schiacciato-star-world",
    "price": "6.5",
    "favourite": 0
  },
  {
    "titre": "LEGO 75344 Boba Fett's Starship Microfigther",
    "lienURL": "https://www.vinted.fr/items/5497624798-lego-75344-boba-fetts-starship-microfigther",
    "price": "9.0",
    "favourite": 4
  },
  {
    "titre": "Lego star Wars",
    "lienURL": "https://www.vinted.fr/items/5425739778-lego-star-wars",
    "price": "4.0",
    "favourite": 0
  },
  {
    "titre": "Lego Star Wars 75344",
    "lienURL": "https://www.vinted.fr/items/5050936835-lego-star-wars-75344",
    "price": "10.0",
    "favourite": 4
  },
  {
    "titre": "Lego 75344 star wars",
    "lienURL": "https://www.vinted.fr/items/5005862645-lego-75344-star-wars",
    "price": "4.0",
    "favourite": 3
  },
  {
    "titre": "Lego Star Wars 75344",
    "lienURL": "https://www.vinted.fr/items/4879178543-lego-star-wars-75344",
    "price": "6.0",
    "favourite": 0
  },
  {
    "titre": "Lego Star Wars 75344 neuf",
    "lienURL": "https://www.vinted.fr/items/5039173989-lego-star-wars-75344-neuf",
    "price": "11.0",
    "favourite": 3
  },
  {
    "titre": "Lego star wars 75344",
    "lienURL": "https://www.vinted.fr/items/3949132970-lego-star-wars-75344",
    "price": "8.5",
    "favourite": 1
  },
  {
    "titre": "Boîte de lego stars wars 75344",
    "lienURL": "https://www.vinted.fr/items/5260831130-boite-de-lego-stars-wars-75344",
    "price": "12.0",
    "favourite": 0
  },
  {
    "titre": "Lego Stars Wars",
    "lienURL": "https://www.vinted.fr/items/5369089931-lego-stars-wars",
    "price": "5.0",
    "favourite": 0
  },
  {
    "titre": "Lego Star Wars ",
    "lienURL": "https://www.vinted.fr/items/3774879576-lego-star-wars",
    "price": "9.0",
    "favourite": 1
  },
  {
    "titre": "Lego star wars 75344 neuf ",
    "lienURL": "https://www.vinted.fr/items/4203807223-lego-star-wars-75344-neuf",
    "price": "8.0",
    "favourite": 5
  },
  {
    "titre": "Lego star wars 75344",
    "lienURL": "https://www.vinted.fr/items/4312412031-lego-star-wars-75344",
    "price": "3.0",
    "favourite": 3
  },
  {
    "titre": "Lego star Wars 75344 Boba Fett’s starship microfighter saled",
    "lienURL": "https://www.vinted.fr/items/4906127397-lego-star-wars-75344-boba-fetts-starship-microfighter-saled",
    "price": "10.0",
    "favourite": 2
  },
  {
    "titre": "Lego star wars 75344",
    "lienURL": "https://www.vinted.fr/items/3993855874-lego-star-wars-75344",
    "price": "5.0",
    "favourite": 1
  },
  {
    "titre": "Lego Star Wars - Boba Fett’s Starship Microfighter ",
    "lienURL": "https://www.vinted.fr/items/4175616870-lego-star-wars-boba-fetts-starship-microfighter",
    "price": "9.0",
    "favourite": 3
  },
  {
    "titre": "Lego 75344",
    "lienURL": "https://www.vinted.fr/items/5247889064-lego-75344",
    "price": "10.0",
    "favourite": 1
  },
  {
    "titre": "LEGO Boba Fetts Starship Microfighter",
    "lienURL": "https://www.vinted.fr/items/5426708624-lego-boba-fetts-starship-microfighter",
    "price": "7.0",
    "favourite": 2
  },
  {
    "titre": "Lego Star Wars 75344",
    "lienURL": "https://www.vinted.fr/items/5479088198-lego-star-wars-75344",
    "price": "7.0",
    "favourite": 1
  },
  {
    "titre": "Lego Star Wars 75344 microfighter Vaisseau de Boobafeth",
    "lienURL": "https://www.vinted.fr/items/5109165387-lego-star-wars-75344-microfighter-vaisseau-de-boobafeth",
    "price": "10.0",
    "favourite": 3
  },
  {
    "titre": "Lego boba fett 75344",
    "lienURL": "https://www.vinted.fr/items/4202297352-lego-boba-fett-75344",
    "price": "10.0",
    "favourite": 1
  },
  {
    "titre": "Star wars",
    "lienURL": "https://www.vinted.fr/items/3889232420-star-wars",
    "price": "12.0",
    "favourite": 1
  },
  {
    "titre": "Lego Star Wars Boba's fett's starship Microfighter  75344 no o",
    "lienURL": "https://www.vinted.fr/items/5492700502-lego-star-wars-bobas-fetts-starship-microfighter-75344-no-o",
    "price": "9.99",
    "favourite": 4
  },
  {
    "titre": "Lego Star Wars 75344 Boba Fett's Starship Microfighter",
    "lienURL": "https://www.vinted.fr/items/4871136807-lego-star-wars-75344-boba-fetts-starship-microfighter",
    "price": "8.0",
    "favourite": 0
  },
  {
    "titre": "Lego Starwars 75344",
    "lienURL": "https://www.vinted.fr/items/5411419027-lego-starwars-75344",
    "price": "9.0",
    "favourite": 0
  },
  {
    "titre": "Compleet set Lego",
    "lienURL": "https://www.vinted.fr/items/4760929787-compleet-set-lego",
    "price": "5.0",
    "favourite": 5
  },
  {
    "titre": "Lego Star Wars #75344 Boba Fett's Starship",
    "lienURL": "https://www.vinted.fr/items/5531974907-lego-star-wars-75344-boba-fetts-starship",
    "price": "7.0",
    "favourite": 2
  },
  {
    "titre": "Lego star wars 75344",
    "lienURL": "https://www.vinted.fr/items/4493345940-lego-star-wars-75344",
    "price": "8.0",
    "favourite": 2
  },
  {
    "titre": "lego star wars 75344 Boba Fett et son vaisseau",
    "lienURL": "https://www.vinted.fr/items/5451921006-lego-star-wars-75344-boba-fett-et-son-vaisseau",
    "price": "5.0",
    "favourite": 3
  },
  {
    "titre": "Lego star Wars Boba Fett's Starship (75344)",
    "lienURL": "https://www.vinted.fr/items/5398651108-lego-star-wars-boba-fetts-starship-75344",
    "price": "9.99",
    "favourite": 1
  },
  {
    "titre": "LEGO 75344 Boba Fett’s Starship Microfighter",
    "lienURL": "https://www.vinted.fr/items/5465143644-lego-75344-boba-fetts-starship-microfighter",
    "price": "7.0",
    "favourite": 2
  },
  {
    "titre": "Lego Star Wars 75344",
    "lienURL": "https://www.vinted.fr/items/4386689393-lego-star-wars-75344",
    "price": "8.0",
    "favourite": 0
  },
  {
    "titre": "Lego star wars 75344",
    "lienURL": "https://www.vinted.fr/items/3870004415-lego-star-wars-75344",
    "price": "15.0",
    "favourite": 5
  }
]